tests/__init__.py
tests/test_timeprofile.py
tests/test_timeprofilecollection.py
timeprofiles/__init__.py
timeprofiles/timeprofile.py
timeprofiles/timeprofilecollection.py
timeprofiles/zoompan.py
timeprofiles-0.0.6.dist-info/LICENSE.txt
timeprofiles-0.0.6.dist-info/METADATA
timeprofiles-0.0.6.dist-info/WHEEL
timeprofiles-0.0.6.dist-info/top_level.txt
timeprofiles-0.0.6.dist-info/RECORD
