Metadata-Version: 2.1
Name: timeprofiles
Version: 0.0.6
Summary: Easily profile time taken for methods to complete. 
Home-page: https://github.com/HansT01/timeprofiles
Author: Hans Teh
Author-email: <hansteh001@gmail.com>
License: UNKNOWN
Keywords: python,time,profile,class,method
Platform: UNKNOWN
Classifier: Development Status :: 2 - Pre-Alpha
Classifier: Intended Audience :: Developers
Classifier: Programming Language :: Python :: 3
Classifier: Programming Language :: Python :: 3.10
Classifier: Operating System :: OS Independent
License-File: LICENSE.txt
Requires-Dist: numpy
Requires-Dist: matplotlib
Requires-Dist: tabulate
Requires-Dist: colorhash
